baton/__init__.py
baton/admin.py
baton/ai.py
baton/apps.py
baton/config.py
baton/fields.py
baton/forms.py
baton/models.py
baton/tests.py
baton/urls.py
baton/views.py
baton/widgets.py
baton/autodiscover/__init__.py
baton/autodiscover/admin.py
baton/locale/fa/LC_MESSAGES/django.mo
baton/locale/fa/LC_MESSAGES/django.po
baton/locale/it/LC_MESSAGES/django.mo
baton/locale/it/LC_MESSAGES/django.po
baton/migrations/0001_initial.py
baton/migrations/0002_alter_batontheme_options_alter_batontheme_active_and_more.py
baton/migrations/__init__.py
baton/static/admin/css/base.css
baton/static/admin/css/changelists.css
baton/static/admin/css/dark_mode.css
baton/static/admin/css/dashboard.css
baton/static/admin/css/forms.css
baton/static/admin/css/responsive.css
baton/static/admin/css/rtl.css
baton/static/admin/img/icon-addlink.svg
baton/static/admin/img/icon-changelink.svg
baton/static/admin/img/icon-deletelink.svg
baton/static/admin/img/icon-hidelink.svg
baton/static/admin/img/icon-viewlink.svg
baton/static/admin/img/search.svg
baton/static/baton/app/.babelrc
baton/static/baton/app/.eslintignore
baton/static/baton/app/.eslintrc
baton/static/baton/app/.prettierrc.json
baton/static/baton/app/.tern-project
baton/static/baton/app/package-lock.json
baton/static/baton/app/package.json
baton/static/baton/app/postcss.config.js
baton/static/baton/app/stats.json
baton/static/baton/app/webpack.common.js
baton/static/baton/app/webpack.dev.js
baton/static/baton/app/webpack.prod.js
baton/static/baton/app/dist/1a6637707f1f349e23bb.ttf
baton/static/baton/app/dist/1c018f34d310f70c6492.ttf
baton/static/baton/app/dist/1d5b13020cf1d7efde67.svg
baton/static/baton/app/dist/585438362096703e90b2.ttf
baton/static/baton/app/dist/62397fb22f9cf321cfcd.svg
baton/static/baton/app/dist/675dd7224206ea211c6e.ttf
baton/static/baton/app/dist/7fd18804f2abd547c565.svg
baton/static/baton/app/dist/820a83e6dbb5ee491646.svg
baton/static/baton/app/dist/baton.min.js
baton/static/baton/app/dist/baton.min.js.LICENSE.txt
django_baton-5.1.0.dist-info/licenses/LICENSE
django_baton-5.1.0.dist-info/METADATA
django_baton-5.1.0.dist-info/WHEEL
django_baton-5.1.0.dist-info/top_level.txt
django_baton-5.1.0.dist-info/RECORD
